{
  "pattern": "Caleido3",
  "params": {
    "SPEED": 0.66,
    "SYMMETRY": 4,
    "TWIST": 4.6000000000000005,
    "COLOR_CYCLE": 0.15,
    "COLORMAP": "rainbow",
    "SPRITE": "none"
  },
  "modulation": {
    "SPEED": {
      "mod_active": false,
      "mod_source": null,
      "mod_mode": "add"
    },
    "SYMMETRY": {
      "mod_active": false,
      "mod_source": null,
      "mod_mode": "add"
    },
    "TWIST": {
      "mod_active": false,
      "mod_source": null,
      "mod_mode": "add"
    },
    "COLOR_CYCLE": {
      "mod_active": false,
      "mod_source": null,
      "mod_mode": "add"
    }
  },
  "lfo_config": {
    "lfo1": {
      "waveform": "sine",
      "depth": 1.0,
      "offset": -0.07,
      "sync_mode": "quantized",
      "hz": 0.5,
      "period_beats": 1.0,
      "phase": 0.0
    },
    "lfo2": {
      "waveform": "triangle",
      "depth": 1.0,
      "offset": -0.03,
      "sync_mode": "free",
      "hz": 0.2,
      "period_beats": 2.0,
      "phase": 0.0
    }
  },
  "env_config": {
    "envl": {
      "threshold_db": 20,
      "gain_db": 10,
      "attack": 0.001,
      "release": 0.025,
      "mode": "down"
    },
    "envh": {
      "threshold_db": -40,
      "gain_db": -40,
      "attack": 0.001,
      "release": 0.025,
      "mode": "down"
    }
  }
}